{
  "date": "2026-01-11T00:00+09:00",
  "character_gender": "남",
  "character_class": "나이트로드",
  "character_look_mode": "0",
  "preset_no": 2,
  "cash_item_equipment_base": [
    {
      "cash_item_equipment_part": "모자",
      "cash_item_equipment_slot": "모자",
      "cash_item_name": "노빌리티 크라운",
      "cash_item_icon": "https://open.api.nexon.com/static/maplestory/item/icon/KEPCNCLF",
      "cash_item_description": null,
      "cash_item_option": [
        {
          "option_type": "DEX",
          "option_value": "30"
        },
        {
          "option_type": "LUK",
          "option_value": "30"
        }
      ],
      "date_expire": null,
      "date_option_expire": "2026-02-23T14:00+09:00",
      "cash_item_label": "마스터라벨",
      "cash_item_coloring_prism": null,
      "cash_item_effect_prism": null,
      "item_gender": null,
      "skills": [],
      "freestyle_flag": "0",
      "emotion_name": null
    },
    {
      "cash_item_equipment_part": "얼굴장식",
      "cash_item_equipment_slot": "얼굴장식",
      "cash_item_name": "홍조 깨비깨비",
      "cash_item_icon": "https://open.api.nexon.com/static/maplestory/item/icon/KEPDJAKJ",
      "cash_item_description": "주의! 커다랗거나 특이한 입매나 큰 눈동자의 일부 성형은 홍조 깨비깨비 얼굴장식 착용 시 성형과 얼굴장식 이미지가 동시 출력되어 캐릭터 얼굴이 어그러져 보일 수 있습니다.",
      "cash_item_option": [],
      "date_expire": null,
      "date_option_expire": null,
      "cash_item_label": null,
      "cash_item_coloring_prism": null,
      "cash_item_effect_prism": null,
      "item_gender": null,
      "skills": [],
      "freestyle_flag": "0",
      "emotion_name": null
    },
    {
      "cash_item_equipment_part": "눈장식",
      "cash_item_equipment_slot": "눈장식",
      "cash_item_name": "투명 안경",
      "cash_item_icon": "https://open.api.nexon.com/static/maplestory/item/icon/KEPAJHJI",
      "cash_item_description": null,
      "cash_item_option": [],
      "date_expire": null,
      "date_option_expire": null,
      "cash_item_label": null,
      "cash_item_coloring_prism": null,
      "cash_item_effect_prism": null,
      "item_gender": null,
      "skills": [],
      "freestyle_flag": "0",
      "emotion_name": null
    },
    {
      "cash_item_equipment_part": "귀고리",
      "cash_item_equipment_slot": "귀고리",
      "cash_item_name": "투명 귀고리",
      "cash_item_icon": "https://open.api.nexon.com/static/maplestory/item/icon/KEPBJHMF",
      "cash_item_description": null,
      "cash_item_option": [],
      "date_expire": null,
      "date_option_expire": null,
      "cash_item_label": null,
      "cash_item_coloring_prism": null,
      "cash_item_effect_prism": null,
      "item_gender": null,
      "skills": [],
      "freestyle_flag": "0",
      "emotion_name": null
    },
    {
      "cash_item_equipment_part": "한벌옷",
      "cash_item_equipment_slot": "상의",
      "cash_item_name": "글로리 세라핌",
      "cash_item_icon": "https://open.api.nexon.com/static/maplestory/item/icon/KEPHLAGB",
      "cash_item_description": null,
      "cash_item_option": [],
      "date_expire": null,
      "date_option_expire": null,
      "cash_item_label": "마스터라벨",
      "cash_item_coloring_prism": null,
      "cash_item_effect_prism": null,
      "item_gender": "남",
      "skills": [],
      "freestyle_flag": "0",
      "emotion_name": null
    },
    {
      "cash_item_equipment_part": "신발",
      "cash_item_equipment_slot": "신발",
      "cash_item_name": "아너 마제스티",
      "cash_item_icon": "https://open.api.nexon.com/static/maplestory/item/icon/KEPFIOLC",
      "cash_item_description": null,
      "cash_item_option": [],
      "date_expire": null,
      "date_option_expire": null,
      "cash_item_label": "마스터라벨",
      "cash_item_coloring_prism": null,
      "cash_item_effect_prism": null,
      "item_gender": null,
      "skills": [],
      "freestyle_flag": "0",
      "emotion_name": null
    },
    {
      "cash_item_equipment_part": "장갑",
      "cash_item_equipment_slot": "장갑",
      "cash_item_name": "이터니티 플레임",
      "cash_item_icon": "https://open.api.nexon.com/static/maplestory/item/icon/KEPKJPKI",
      "cash_item_description": null,
      "cash_item_option": [],
      "date_expire": null,
      "date_option_expire": null,
      "cash_item_label": null,
      "cash_item_coloring_prism": null,
      "cash_item_effect_prism": null,
      "item_gender": null,
      "skills": [],
      "freestyle_flag": "0",
      "emotion_name": null
    },
    {
      "cash_item_equipment_part": "망토",
      "cash_item_equipment_slot": "망토",
      "cash_item_name": "가디언 세라핌 페더",
      "cash_item_icon": "https://open.api.nexon.com/static/maplestory/item/icon/KEOCIANC",
      "cash_item_description": null,
      "cash_item_option": [
        {
          "option_type": "LUK",
          "option_value": "30"
        }
      ],
      "date_expire": null,
      "date_option_expire": "2026-02-24T22:00+09:00",
      "cash_item_label": "마스터라벨",
      "cash_item_coloring_prism": null,
      "cash_item_effect_prism": null,
      "item_gender": null,
      "skills": [],
      "freestyle_flag": "0",
      "emotion_name": null
    },
    {
      "cash_item_equipment_part": "무기",
      "cash_item_equipment_slot": "무기",
      "cash_item_name": "디바인 그레이스",
      "cash_item_icon": "https://open.api.nexon.com/static/maplestory/item/icon/KEICICMC",
      "cash_item_description": "모든 무기에 착용이 가능한 무기이다. 착용 시 걷기, 점프, 밧줄 및 사다리 타기, 날기 동작에서 특별한 세라핌 이펙트가 출력된다.",
      "cash_item_option": [
        {
          "option_type": "공격력",
          "option_value": "30"
        },
        {
          "option_type": "마력",
          "option_value": "30"
        }
      ],
      "date_expire": null,
      "date_option_expire": "2026-02-24T22:00+09:00",
      "cash_item_label": "마스터라벨",
      "cash_item_coloring_prism": null,
      "cash_item_effect_prism": null,
      "item_gender": null,
      "skills": [],
      "freestyle_flag": "0",
      "emotion_name": null
    }
  ],
  "cash_item_equipment_preset_1": [],
  "cash_item_equipment_preset_2": [
    {
      "cash_item_equipment_part": "모자",
      "cash_item_equipment_slot": "모자",
      "cash_item_name": "메르헨 프린세스",
      "cash_item_icon": "https://open.api.nexon.com/static/maplestory/item/icon/KEPCNEGG",
      "cash_item_description": null,
      "cash_item_option": [],
      "date_expire": null,
      "date_option_expire": null,
      "cash_item_label": "마스터라벨",
      "cash_item_coloring_prism": null,
      "cash_item_effect_prism": null,
      "item_gender": null,
      "skills": [],
      "freestyle_flag": "0",
      "emotion_name": null
    },
    {
      "cash_item_equipment_part": "한벌옷",
      "cash_item_equipment_slot": "상의",
      "cash_item_name": "별의 소원",
      "cash_item_icon": "https://open.api.nexon.com/static/maplestory/item/icon/KEPHLAMI",
      "cash_item_description": null,
      "cash_item_option": [],
      "date_expire": null,
      "date_option_expire": null,
      "cash_item_label": "마스터라벨",
      "cash_item_coloring_prism": null,
      "cash_item_effect_prism": null,
      "item_gender": "남",
      "skills": [],
      "freestyle_flag": "0",
      "emotion_name": null
    },
    {
      "cash_item_equipment_part": "신발",
      "cash_item_equipment_slot": "신발",
      "cash_item_name": "카트시 부츠",
      "cash_item_icon": "https://open.api.nexon.com/static/maplestory/item/icon/KEPFLGJC",
      "cash_item_description": null,
      "cash_item_option": [],
      "date_expire": null,
      "date_option_expire": null,
      "cash_item_label": "마스터라벨",
      "cash_item_coloring_prism": null,
      "cash_item_effect_prism": null,
      "item_gender": "남",
      "skills": [],
      "freestyle_flag": "0",
      "emotion_name": null
    },
    {
      "cash_item_equipment_part": "망토",
      "cash_item_equipment_slot": "망토",
      "cash_item_name": "메르헨 캐슬",
      "cash_item_icon": "https://open.api.nexon.com/static/maplestory/item/icon/KEOCIBLE",
      "cash_item_description": null,
      "cash_item_option": [],
      "date_expire": null,
      "date_option_expire": null,
      "cash_item_label": "마스터라벨",
      "cash_item_coloring_prism": null,
      "cash_item_effect_prism": null,
      "item_gender": null,
      "skills": [],
      "freestyle_flag": "0",
      "emotion_name": null
    },
    {
      "cash_item_equipment_part": "무기",
      "cash_item_equipment_slot": "무기",
      "cash_item_name": "페어리 래빗",
      "cash_item_icon": "https://open.api.nexon.com/static/maplestory/item/icon/KEICIDMH",
      "cash_item_description": "모든 무기에 착용이 가능한 무기이다. 착용 시 걷기, 점프, 밧줄 및 사다리 타기 동작에서 특별한 메르헨 이펙트가 출력된다.",
      "cash_item_option": [],
      "date_expire": null,
      "date_option_expire": null,
      "cash_item_label": "마스터라벨",
      "cash_item_coloring_prism": null,
      "cash_item_effect_prism": null,
      "item_gender": null,
      "skills": [],
      "freestyle_flag": "0",
      "emotion_name": null
    }
  ],
  "cash_item_equipment_preset_3": [
    {
      "cash_item_equipment_part": "모자",
      "cash_item_equipment_slot": "모자",
      "cash_item_name": "빨간 눈사람 모자",
      "cash_item_icon": "https://open.api.nexon.com/static/maplestory/item/icon/KEPCODGA",
      "cash_item_description": null,
      "cash_item_option": [],
      "date_expire": null,
      "date_option_expire": null,
      "cash_item_label": null,
      "cash_item_coloring_prism": null,
      "cash_item_effect_prism": null,
      "item_gender": null,
      "skills": [],
      "freestyle_flag": "0",
      "emotion_name": null
    },
    {
      "cash_item_equipment_part": "얼굴장식",
      "cash_item_equipment_slot": "얼굴장식",
      "cash_item_name": "투명 얼굴장식",
      "cash_item_icon": "https://open.api.nexon.com/static/maplestory/item/icon/KEPDJFGI",
      "cash_item_description": null,
      "cash_item_option": [],
      "date_expire": null,
      "date_option_expire": null,
      "cash_item_label": null,
      "cash_item_coloring_prism": null,
      "cash_item_effect_prism": null,
      "item_gender": null,
      "skills": [],
      "freestyle_flag": "0",
      "emotion_name": null
    },
    {
      "cash_item_equipment_part": "눈장식",
      "cash_item_equipment_slot": "눈장식",
      "cash_item_name": "까만 선글라스",
      "cash_item_icon": "https://open.api.nexon.com/static/maplestory/item/icon/KEPAJHOF",
      "cash_item_description": null,
      "cash_item_option": [],
      "date_expire": null,
      "date_option_expire": null,
      "cash_item_label": null,
      "cash_item_coloring_prism": null,
      "cash_item_effect_prism": null,
      "item_gender": null,
      "skills": [],
      "freestyle_flag": "0",
      "emotion_name": null
    },
    {
      "cash_item_equipment_part": "한벌옷",
      "cash_item_equipment_slot": "상의",
      "cash_item_name": "루돌프 베리 후디",
      "cash_item_icon": "https://open.api.nexon.com/static/maplestory/item/icon/KEPHIOKF",
      "cash_item_description": null,
      "cash_item_option": [],
      "date_expire": null,
      "date_option_expire": null,
      "cash_item_label": null,
      "cash_item_coloring_prism": null,
      "cash_item_effect_prism": null,
      "item_gender": null,
      "skills": [],
      "freestyle_flag": "0",
      "emotion_name": null
    },
    {
      "cash_item_equipment_part": "신발",
      "cash_item_equipment_slot": "신발",
      "cash_item_name": "투명 신발",
      "cash_item_icon": "https://open.api.nexon.com/static/maplestory/item/icon/KEPFJGLC",
      "cash_item_description": null,
      "cash_item_option": [],
      "date_expire": null,
      "date_option_expire": null,
      "cash_item_label": null,
      "cash_item_coloring_prism": null,
      "cash_item_effect_prism": null,
      "item_gender": null,
      "skills": [],
      "freestyle_flag": "0",
      "emotion_name": null
    },
    {
      "cash_item_equipment_part": "장갑",
      "cash_item_equipment_slot": "장갑",
      "cash_item_name": "투명 장갑",
      "cash_item_icon": "https://open.api.nexon.com/static/maplestory/item/icon/KEPKJGOD",
      "cash_item_description": null,
      "cash_item_option": [],
      "date_expire": null,
      "date_option_expire": null,
      "cash_item_label": null,
      "cash_item_coloring_prism": null,
      "cash_item_effect_prism": null,
      "item_gender": null,
      "skills": [],
      "freestyle_flag": "0",
      "emotion_name": null
    },
    {
      "cash_item_equipment_part": "망토",
      "cash_item_equipment_slot": "망토",
      "cash_item_name": "스피릿 나인테일",
      "cash_item_icon": "https://open.api.nexon.com/static/maplestory/item/icon/KEOCJBHE",
      "cash_item_description": "구미호들이 자랑하는 풍성한 꼬리. 교환이 불가능한 아이템입니다.",
      "cash_item_option": [],
      "date_expire": null,
      "date_option_expire": null,
      "cash_item_label": null,
      "cash_item_coloring_prism": null,
      "cash_item_effect_prism": null,
      "item_gender": null,
      "skills": [],
      "freestyle_flag": "0",
      "emotion_name": null
    },
    {
      "cash_item_equipment_part": "무기",
      "cash_item_equipment_slot": "무기",
      "cash_item_name": "꽃보다 나비",
      "cash_item_icon": "https://open.api.nexon.com/static/maplestory/item/icon/KEICJGJF",
      "cash_item_description": "모든 무기에 착용이 가능한 무기이다.",
      "cash_item_option": [],
      "date_expire": null,
      "date_option_expire": null,
      "cash_item_label": null,
      "cash_item_coloring_prism": null,
      "cash_item_effect_prism": null,
      "item_gender": null,
      "skills": [],
      "freestyle_flag": "0",
      "emotion_name": null
    },
    {
      "cash_item_equipment_part": "반지",
      "cash_item_equipment_slot": "반지2",
      "cash_item_name": "세이비어 말풍선 반지",
      "cash_item_icon": "https://open.api.nexon.com/static/maplestory/item/icon/KEODOFJC",
      "cash_item_description": "캐릭터가 대화를 할 때, 세이비어 말풍선이 나타난다.",
      "cash_item_option": [],
      "date_expire": null,
      "date_option_expire": null,
      "cash_item_label": null,
      "cash_item_coloring_prism": null,
      "cash_item_effect_prism": null,
      "item_gender": null,
      "skills": [],
      "freestyle_flag": "0",
      "emotion_name": null
    },
    {
      "cash_item_equipment_part": "반지",
      "cash_item_equipment_slot": "반지3",
      "cash_item_name": "세이비어 명찰 반지",
      "cash_item_icon": "https://open.api.nexon.com/static/maplestory/item/icon/KEODOEJE",
      "cash_item_description": "캐릭터 이름이 세이비어 명찰에 나타난다.",
      "cash_item_option": [],
      "date_expire": null,
      "date_option_expire": null,
      "cash_item_label": null,
      "cash_item_coloring_prism": null,
      "cash_item_effect_prism": null,
      "item_gender": null,
      "skills": [],
      "freestyle_flag": "0",
      "emotion_name": null
    }
  ],
  "additional_cash_item_equipment_base": [],
  "additional_cash_item_equipment_preset_1": [],
  "additional_cash_item_equipment_preset_2": [],
  "additional_cash_item_equipment_preset_3": []
}