{
  "date": "2026-01-11T00:00+09:00",
  "character_gender": "남",
  "character_class": "에반",
  "character_look_mode": "0",
  "preset_no": 2,
  "cash_item_equipment_base": [
    {
      "cash_item_equipment_part": "모자",
      "cash_item_equipment_slot": "모자",
      "cash_item_name": "혼돈의 명령",
      "cash_item_icon": "https://open.api.nexon.com/static/maplestory/item/icon/KEPCNOOJ",
      "cash_item_description": null,
      "cash_item_option": [
        {
          "option_type": "INT",
          "option_value": "30"
        }
      ],
      "date_expire": null,
      "date_option_expire": "2026-09-04T05:00+09:00",
      "cash_item_label": "마스터라벨",
      "cash_item_coloring_prism": null,
      "cash_item_effect_prism": null,
      "item_gender": null,
      "skills": [],
      "freestyle_flag": "0",
      "emotion_name": null
    },
    {
      "cash_item_equipment_part": "눈장식",
      "cash_item_equipment_slot": "눈장식",
      "cash_item_name": "투명 안경",
      "cash_item_icon": "https://open.api.nexon.com/static/maplestory/item/icon/KEPAJHJI",
      "cash_item_description": null,
      "cash_item_option": [],
      "date_expire": null,
      "date_option_expire": null,
      "cash_item_label": null,
      "cash_item_coloring_prism": null,
      "cash_item_effect_prism": null,
      "item_gender": null,
      "skills": [],
      "freestyle_flag": "0",
      "emotion_name": null
    },
    {
      "cash_item_equipment_part": "귀고리",
      "cash_item_equipment_slot": "귀고리",
      "cash_item_name": "투명 귀고리",
      "cash_item_icon": "https://open.api.nexon.com/static/maplestory/item/icon/KEPBJHMF",
      "cash_item_description": null,
      "cash_item_option": [],
      "date_expire": null,
      "date_option_expire": null,
      "cash_item_label": null,
      "cash_item_coloring_prism": null,
      "cash_item_effect_prism": null,
      "item_gender": null,
      "skills": [],
      "freestyle_flag": "0",
      "emotion_name": null
    },
    {
      "cash_item_equipment_part": "한벌옷",
      "cash_item_equipment_slot": "상의",
      "cash_item_name": "파멸의 계약",
      "cash_item_icon": "https://open.api.nexon.com/static/maplestory/item/icon/KEPHLPNG",
      "cash_item_description": null,
      "cash_item_option": [
        {
          "option_type": "방어력",
          "option_value": "300"
        }
      ],
      "date_expire": null,
      "date_option_expire": "2026-09-04T20:00+09:00",
      "cash_item_label": "마스터라벨",
      "cash_item_coloring_prism": null,
      "cash_item_effect_prism": null,
      "item_gender": "남",
      "skills": [],
      "freestyle_flag": "0",
      "emotion_name": null
    },
    {
      "cash_item_equipment_part": "신발",
      "cash_item_equipment_slot": "신발",
      "cash_item_name": "파멸의 궤적",
      "cash_item_icon": "https://open.api.nexon.com/static/maplestory/item/icon/KEPFPFND",
      "cash_item_description": null,
      "cash_item_option": [
        {
          "option_type": "이동속도",
          "option_value": "50"
        },
        {
          "option_type": "점프력",
          "option_value": "50"
        }
      ],
      "date_expire": null,
      "date_option_expire": "2026-09-01T20:00+09:00",
      "cash_item_label": "마스터라벨",
      "cash_item_coloring_prism": null,
      "cash_item_effect_prism": null,
      "item_gender": null,
      "skills": [],
      "freestyle_flag": "0",
      "emotion_name": null
    },
    {
      "cash_item_equipment_part": "장갑",
      "cash_item_equipment_slot": "장갑",
      "cash_item_name": "투명 장갑",
      "cash_item_icon": "https://open.api.nexon.com/static/maplestory/item/icon/KEPKJGOD",
      "cash_item_description": null,
      "cash_item_option": [],
      "date_expire": null,
      "date_option_expire": null,
      "cash_item_label": null,
      "cash_item_coloring_prism": null,
      "cash_item_effect_prism": null,
      "item_gender": null,
      "skills": [],
      "freestyle_flag": "0",
      "emotion_name": null
    },
    {
      "cash_item_equipment_part": "망토",
      "cash_item_equipment_slot": "망토",
      "cash_item_name": "혼돈의 결속",
      "cash_item_icon": "https://open.api.nexon.com/static/maplestory/item/icon/KEOCIOPH",
      "cash_item_description": null,
      "cash_item_option": [
        {
          "option_type": "DEX",
          "option_value": "30"
        },
        {
          "option_type": "INT",
          "option_value": "30"
        },
        {
          "option_type": "LUK",
          "option_value": "30"
        }
      ],
      "date_expire": null,
      "date_option_expire": "2026-09-05T00:00+09:00",
      "cash_item_label": "마스터라벨",
      "cash_item_coloring_prism": null,
      "cash_item_effect_prism": null,
      "item_gender": null,
      "skills": [],
      "freestyle_flag": "0",
      "emotion_name": null
    },
    {
      "cash_item_equipment_part": "무기",
      "cash_item_equipment_slot": "무기",
      "cash_item_name": "카오스 크레센트",
      "cash_item_icon": "https://open.api.nexon.com/static/maplestory/item/icon/KEICIAMA",
      "cash_item_description": "모든 무기에 착용이 가능한 무기이다. 착용 시 특별한 카오스 이펙트가 출력된다.",
      "cash_item_option": [
        {
          "option_type": "마력",
          "option_value": "30"
        }
      ],
      "date_expire": null,
      "date_option_expire": "2026-09-04T20:00+09:00",
      "cash_item_label": "마스터라벨",
      "cash_item_coloring_prism": null,
      "cash_item_effect_prism": null,
      "item_gender": null,
      "skills": [],
      "freestyle_flag": "0",
      "emotion_name": null
    },
    {
      "cash_item_equipment_part": "반지",
      "cash_item_equipment_slot": "반지1",
      "cash_item_name": "혈맹의 반지",
      "cash_item_icon": "https://open.api.nexon.com/static/maplestory/item/icon/KEODPHOE",
      "cash_item_description": "혈맹의 수호로 반지 착용자는 사냥 시 10%의 혈맹 보너스 경험치를 획득할 수 있다. 혈맹의 반지 착용자가 파티에 늘어날수록 한 명 당 5%씩의 혈맹 보너스 경험치를 추가로 받을 수 있다. 혈맹의 반지는 1개만 착용할 수 있고 파티원이 동일한 맵 내에 위치해야 효과를 받을 수 있다.     본인 착용시 10% 보너스 경험치   1인 추가 착용 시 15% 보너스 경험치   2인 추가 착용 시 20% 보너스 경험치   3인 추가 착용 시 25% 보너스 경험치   4인 추가 착용 시 30% 보너스 경험치",
      "cash_item_option": [],
      "date_expire": "2026-01-15T00:00+09:00",
      "date_option_expire": null,
      "cash_item_label": null,
      "cash_item_coloring_prism": null,
      "cash_item_effect_prism": null,
      "item_gender": null,
      "skills": [],
      "freestyle_flag": "0",
      "emotion_name": null
    },
    {
      "cash_item_equipment_part": "반지",
      "cash_item_equipment_slot": "반지2",
      "cash_item_name": "경험치 부스트 링(15%)",
      "cash_item_icon": "https://open.api.nexon.com/static/maplestory/item/icon/KEODPENB",
      "cash_item_description": "장착 후 사냥 시 경험치 부스트 링의 효과를 받아 15% 추가 경험치를 획득한다. 단, 부스트 링 종류의 반지는 중복하여 장착할 수 없습니다.",
      "cash_item_option": [],
      "date_expire": "2026-01-15T00:00+09:00",
      "date_option_expire": null,
      "cash_item_label": null,
      "cash_item_coloring_prism": null,
      "cash_item_effect_prism": null,
      "item_gender": null,
      "skills": [],
      "freestyle_flag": "0",
      "emotion_name": null
    }
  ],
  "cash_item_equipment_preset_1": [],
  "cash_item_equipment_preset_2": [
    {
      "cash_item_equipment_part": "모자",
      "cash_item_equipment_slot": "모자",
      "cash_item_name": "드림 리본",
      "cash_item_icon": "https://open.api.nexon.com/static/maplestory/item/icon/KEPCNEKANKBBCPHALH",
      "cash_item_description": null,
      "cash_item_option": [],
      "date_expire": null,
      "date_option_expire": null,
      "cash_item_label": "블랙라벨",
      "cash_item_coloring_prism": {
        "color_range": "전체 색상 계열",
        "hue": 330,
        "saturation": -1,
        "value": -85
      },
      "cash_item_effect_prism": null,
      "item_gender": null,
      "skills": [],
      "freestyle_flag": "0",
      "emotion_name": null
    },
    {
      "cash_item_equipment_part": "얼굴장식",
      "cash_item_equipment_slot": "얼굴장식",
      "cash_item_name": "과묵 반창고",
      "cash_item_icon": "https://open.api.nexon.com/static/maplestory/item/icon/KEPDJBNA",
      "cash_item_description": null,
      "cash_item_option": [],
      "date_expire": null,
      "date_option_expire": null,
      "cash_item_label": null,
      "cash_item_coloring_prism": null,
      "cash_item_effect_prism": null,
      "item_gender": null,
      "skills": [],
      "freestyle_flag": "0",
      "emotion_name": null
    },
    {
      "cash_item_equipment_part": "한벌옷",
      "cash_item_equipment_slot": "상의",
      "cash_item_name": "인기 스타",
      "cash_item_icon": "https://open.api.nexon.com/static/maplestory/item/icon/KEPHLAPENKBDGDFELM",
      "cash_item_description": null,
      "cash_item_option": [],
      "date_expire": null,
      "date_option_expire": null,
      "cash_item_label": "스페셜라벨",
      "cash_item_coloring_prism": {
        "color_range": "전체 색상 계열",
        "hue": 355,
        "saturation": -1,
        "value": -92
      },
      "cash_item_effect_prism": null,
      "item_gender": "남",
      "skills": [],
      "freestyle_flag": "0",
      "emotion_name": null
    },
    {
      "cash_item_equipment_part": "신발",
      "cash_item_equipment_slot": "신발",
      "cash_item_name": "투명 신발",
      "cash_item_icon": "https://open.api.nexon.com/static/maplestory/item/icon/KEPFJGLC",
      "cash_item_description": null,
      "cash_item_option": [],
      "date_expire": null,
      "date_option_expire": null,
      "cash_item_label": null,
      "cash_item_coloring_prism": null,
      "cash_item_effect_prism": null,
      "item_gender": null,
      "skills": [],
      "freestyle_flag": "0",
      "emotion_name": null
    },
    {
      "cash_item_equipment_part": "망토",
      "cash_item_equipment_slot": "망토",
      "cash_item_name": "포실 반디",
      "cash_item_icon": "https://open.api.nexon.com/static/maplestory/item/icon/KEOCIPJBNKDAEKFBBI",
      "cash_item_description": null,
      "cash_item_option": [],
      "date_expire": null,
      "date_option_expire": null,
      "cash_item_label": "스페셜라벨",
      "cash_item_coloring_prism": {
        "color_range": "전체 색상 계열",
        "hue": 0,
        "saturation": -99,
        "value": 40
      },
      "cash_item_effect_prism": null,
      "item_gender": null,
      "skills": [],
      "freestyle_flag": "0",
      "emotion_name": null
    },
    {
      "cash_item_equipment_part": "방패",
      "cash_item_equipment_slot": "보조무기",
      "cash_item_name": "투명 방패",
      "cash_item_icon": "https://open.api.nexon.com/static/maplestory/item/icon/KEPLJHIG",
      "cash_item_description": "방패 및 소울링, 컨트롤러 외에도 보조무기를 착용 중이라면 투명 방패를 착용할 수 있습니다.",
      "cash_item_option": [],
      "date_expire": null,
      "date_option_expire": null,
      "cash_item_label": null,
      "cash_item_coloring_prism": null,
      "cash_item_effect_prism": null,
      "item_gender": null,
      "skills": [],
      "freestyle_flag": "0",
      "emotion_name": null
    },
    {
      "cash_item_equipment_part": "무기",
      "cash_item_equipment_slot": "무기",
      "cash_item_name": "투명 무기",
      "cash_item_icon": "https://open.api.nexon.com/static/maplestory/item/icon/KEICIGMI",
      "cash_item_description": "블레이드를 제외한 모든 무기에 착용이 가능한 투명한 무기이다.",
      "cash_item_option": [],
      "date_expire": null,
      "date_option_expire": null,
      "cash_item_label": null,
      "cash_item_coloring_prism": null,
      "cash_item_effect_prism": null,
      "item_gender": null,
      "skills": [],
      "freestyle_flag": "0",
      "emotion_name": null
    },
    {
      "cash_item_equipment_part": "반지",
      "cash_item_equipment_slot": "반지1",
      "cash_item_name": "싱크 명찰 반지",
      "cash_item_icon": "https://open.api.nexon.com/static/maplestory/item/icon/KEODOCPJ",
      "cash_item_description": "캐릭터 이름이 싱크 명찰(영구)에 나타난다.",
      "cash_item_option": [],
      "date_expire": null,
      "date_option_expire": null,
      "cash_item_label": null,
      "cash_item_coloring_prism": null,
      "cash_item_effect_prism": null,
      "item_gender": null,
      "skills": [],
      "freestyle_flag": "0",
      "emotion_name": null
    },
    {
      "cash_item_equipment_part": "반지",
      "cash_item_equipment_slot": "반지2",
      "cash_item_name": "싱크 말풍선 반지",
      "cash_item_icon": "https://open.api.nexon.com/static/maplestory/item/icon/KEODODPH",
      "cash_item_description": "캐릭터가 대화를 할 때, 싱크 말풍선이 나타난다.",
      "cash_item_option": [],
      "date_expire": null,
      "date_option_expire": null,
      "cash_item_label": null,
      "cash_item_coloring_prism": null,
      "cash_item_effect_prism": null,
      "item_gender": null,
      "skills": [],
      "freestyle_flag": "0",
      "emotion_name": null
    }
  ],
  "cash_item_equipment_preset_3": [],
  "additional_cash_item_equipment_base": [],
  "additional_cash_item_equipment_preset_1": [],
  "additional_cash_item_equipment_preset_2": [],
  "additional_cash_item_equipment_preset_3": []
}